pydwanimes/__init__.py
pydwanimes/cli.py
pydwanimes/application/__init__.py
pydwanimes/application/config.py
pydwanimes/application/helper.py
pydwanimes/application/loading/__init__.py
pydwanimes/application/loading/tqdm_loading.py
pydwanimes/application/players/__init__.py
pydwanimes/application/players/fembed.py
pydwanimes/application/players/fireload.py
pydwanimes/application/players/your_upload.py
pydwanimes/application/sites/__init__.py
pydwanimes/application/sites/anime_fenix.py
pydwanimes/domain/__init__.py
pydwanimes/domain/loading.py
pydwanimes/domain/player.py
pydwanimes/domain/site.py
dwanimes-0.1.7.dist-info/METADATA
dwanimes-0.1.7.dist-info/WHEEL
dwanimes-0.1.7.dist-info/entry_points.txt
dwanimes-0.1.7.dist-info/top_level.txt
dwanimes-0.1.7.dist-info/RECORD
