Metadata-Version: 2.1
Name: dwanimes
Version: 0.1.7
Summary: Download your anime
Home-page: https://github.com/jbuendia1y/download-animes
Author: jbuendia1y (Joaquín Buendía)
Keywords: download,anime
